./.gitignore
./CRCA.py
./LICENSE
./MANIFEST.in
./PKG-INFO
./README.md
./__init__.py
./pyproject.toml
./requirements.txt
./.github/PULL_REQUEST_TEMPLATE.md
./.github/ISSUE_TEMPLATE/bug_report.md
./.github/ISSUE_TEMPLATE/feature_request.md
./.github/workflows/publish-manual.yml
./.github/workflows/publish.yml
./branches/CRCA-Q.py
./branches/crca_cg/corposwarm.py
./branches/crca_cg/fix_rancher_docker_creds.ps1
./branches/crca_cg/package.json
./branches/crca_cg/test_bolt_integration.py
./branches/crca_cg/test_corposwarm_comprehensive.py
./branches/crca_cg/test_new_features.py
./branches/crca_sd/__init__.py
./branches/crca_sd/crca_sd_core.py
./branches/crca_sd/crca_sd_governance.py
./branches/crca_sd/crca_sd_mpc.py
./branches/crca_sd/crca_sd_realtime.py
./branches/crca_sd/crca_sd_tui.py
./docs/CRCA-Q.md
./examples/config.yaml.example
./examples/crca_sd_example.py
./examples/data_broker_example.py
./examples/logistics_corporation.py
./examples/palantir_example.py
./examples/policy_bench.py
./examples/pridnestrovia-sd.py
./examples/pridnestrovia_realtime.py
./prompts/__init__.py
./prompts/default_crca.py
./schemas/__init__.py
./schemas/mcpSchemas.py
./schemas/policy.py
./templates/__init__.py
./templates/base_specialized_agent.py
./templates/drift_detection.py
./templates/feature_mixins.py
./templates/graph_management.py
./templates/llm_integration.py
./templates/module_registry.py
./templates/mpc_planner.py
./templates/policy_loop.py
./templates/prediction_framework.py
./templates/statistical_methods.py
./templates/examples/causal_agent_template.py
./templates/examples/drag_drop_example.py
./templates/examples/logistics_agent_template.py
./templates/examples/trading_agent_template.py
./tests/sanity.yml
./tests/sanity_check
./tests/test_core.py
./tests/test_crca_excel.py
./tests/test_crca_sd.py
./tests/test_data_broker.py
./tests/test_palantir.py
./tools/__init__.py
./tools/actuators.py
./tools/code_generator.py
./tools/file_operations.py
./tools/mandate_generator.py
crca-1.4.0.dist-info/METADATA
crca-1.4.0.dist-info/WHEEL
crca-1.4.0.dist-info/licenses/LICENSE
crca-1.4.0.dist-info/RECORD
