Metadata-Version: 2.4
Name: crca
Version: 1.4.0
Summary: CR-CA Lite — lightweight causal reasoning agent with advanced analysis suite (CR-CA)
Project-URL: Homepage, https://github.com/IlumCI/CR-CA
Project-URL: Repository, https://github.com/IlumCI/CR-CA
Project-URL: Documentation, https://github.com/IlumCI/CR-CA/blob/main/README.md
Project-URL: Issues, https://github.com/IlumCI/CR-CA/issues
Author-email: Ilum <a.leilionas@vk.com>
License: Apache-2.0
License-File: LICENSE
Keywords: causal-reasoning,counterfactual-analysis,data-science,governance,llm,machine-learning,optimization,socioeconomic-dynamics,structural-causal-models,trading
Classifier: Development Status :: 4 - Beta
Classifier: Intended Audience :: Developers
Classifier: Intended Audience :: Science/Research
Classifier: License :: OSI Approved :: Apache Software License
Classifier: Operating System :: OS Independent
Classifier: Programming Language :: Python :: 3
Classifier: Programming Language :: Python :: 3.10
Classifier: Programming Language :: Python :: 3.11
Classifier: Programming Language :: Python :: 3.12
Classifier: Programming Language :: Python :: 3.13
Classifier: Topic :: Scientific/Engineering :: Artificial Intelligence
Classifier: Topic :: Scientific/Engineering :: Information Analysis
Classifier: Topic :: Software Development :: Libraries :: Python Modules
Requires-Python: >=3.10
Requires-Dist: ccxt>=4.0
Requires-Dist: dowhy>=0.8
Requires-Dist: geoip2>=4.7.0
Requires-Dist: lightgbm>=4.0
Requires-Dist: litellm>=0.1
Requires-Dist: loguru>=0.7
Requires-Dist: matplotlib>=3.5
Requires-Dist: mcp>=0.9.0
Requires-Dist: networkx>=3.0
Requires-Dist: numba>=0.58
Requires-Dist: numpy>=1.23
Requires-Dist: openai>=1.0.0
Requires-Dist: optuna>=3.0
Requires-Dist: pandas>=1.5
Requires-Dist: pillow>=10.0
Requires-Dist: praw>=7.0
Requires-Dist: psutil>=5.9.0
Requires-Dist: pycoingecko>=3.0
Requires-Dist: pydantic>=2.0
Requires-Dist: python-dateutil>=2.8
Requires-Dist: python-dotenv>=1.0
Requires-Dist: pytrends>=4.8.0
Requires-Dist: pyyaml>=6.0
Requires-Dist: redis>=5.0
Requires-Dist: reportlab>=4.0.0
Requires-Dist: requests>=2.28
Requires-Dist: rich>=13.0
Requires-Dist: rustworkx>=0.12.0
Requires-Dist: scikit-learn>=1.3
Requires-Dist: scipy>=1.10
Requires-Dist: seaborn>=0.11
Requires-Dist: shodan>=1.30.0
Requires-Dist: swarms
Requires-Dist: toml>=0.10.2
Requires-Dist: torch>=2.0.0
Requires-Dist: tqdm>=4.65.0
Requires-Dist: web3>=6.0
Requires-Dist: websockets>=11.0
Requires-Dist: xgboost>=2.0
Requires-Dist: yfinance>=0.2.0
Provides-Extra: dev
Requires-Dist: black>=23.0; extra == 'dev'
Requires-Dist: mypy>=1.0; extra == 'dev'
Requires-Dist: pytest-cov>=4.0; extra == 'dev'
Requires-Dist: pytest>=7.0; extra == 'dev'
Requires-Dist: ruff>=0.1.0; extra == 'dev'
Provides-Extra: optimization
Requires-Dist: cvxpy>=1.4; extra == 'optimization'
